jupnotipy/__init__.py
jupnotipy/cli.py
jupnotipy/core.py
jupnotipy/funny_messages.py
jupnotipy-0.1.7.dist-info/LICENCE
jupnotipy-0.1.7.dist-info/METADATA
jupnotipy-0.1.7.dist-info/WHEEL
jupnotipy-0.1.7.dist-info/entry_points.txt
jupnotipy-0.1.7.dist-info/RECORD
