Metadata-Version: 2.1
Name: jupnotipy
Version: 0.1.7
Summary: 
Home-page: https://github.com/IlyaKaftanov/jupnotipy
Author: Ilia Kaftanov
Requires-Python: >=3.9,<4.0
Classifier: Programming Language :: Python :: 3
Classifier: Programming Language :: Python :: 3.9
Classifier: Programming Language :: Python :: 3.10
Classifier: Programming Language :: Python :: 3.11
Classifier: Programming Language :: Python :: 3.12
Requires-Dist: requests (>=2.32.3,<3.0.0)
Project-URL: Repository, https://github.com/IlyaKaftanov/jupnotipy
